[{"inputs":[{"internalType":"string","name":"name","type":"string"},{"internalType":"uint256","name":"dateTime","type":"uint256"}],"name":"addTask","outputs":[],"stateMutability":"nonpayable","type":"function"},{"inputs":[{"internalType":"uint256","name":"taskId","type":"uint256"}],"name":"deleteTask","outputs":[],"stateMutability":"nonpayable","type":"function"},{"inputs":[{"internalType":"address","name":"","type":"address"},{"internalType":"uint256","name":"","type":"uint256"}],"name":"ownerTasks","outputs":[{"internalType":"uint256","name":"","type":"uint256"}],"stateMutability":"view","type":"function"},{"inputs":[{"internalType":"uint256","name":"","type":"uint256"}],"name":"tasks","outputs":[{"internalType":"uint256","name":"id","type":"uint256"},{"internalType":"string","name":"name","type":"string"},{"internalType":"uint256","name":"date","type":"uint256"},{"internalType":"address","name":"owner","type":"address"}],"stateMutability":"view","type":"function"},{"inputs":[],"name":"totalTask","outputs":[{"internalType":"uint256","name":"","type":"uint256"}],"stateMutability":"view","type":"function"},{"inputs":[{"internalType":"uint256","name":"taskId","type":"uint256"},{"internalType":"string","name":"name","type":"string"},{"internalType":"uint256","name":"dateTime","type":"uint256"}],"name":"updateTask","outputs":[],"stateMutability":"nonpayable","type":"function"},{"inputs":[],"name":"viewAllTasks","outputs":[{"components":[{"internalType":"uint256","name":"id","type":"uint256"},{"internalType":"string","name":"name","type":"string"},{"internalType":"uint256","name":"date","type":"uint256"},{"internalType":"address","name":"owner","type":"address"}],"internalType":"struct Task[]","name":"","type":"tuple[]"}],"stateMutability":"view","type":"function"},{"inputs":[{"internalType":"address","name":"owner","type":"address"}],"name":"viewUserTasks","outputs":[{"components":[{"internalType":"uint256","name":"id","type":"uint256"},{"internalType":"string","name":"name","type":"string"},{"internalType":"uint256","name":"date","type":"uint256"},{"internalType":"address","name":"owner","type":"address"}],"internalType":"struct Task[]","name":"","type":"tuple[]"}],"stateMutability":"view","type":"function"}]